example2/__init__.py
example2/example_aspp.py
example2-0.1.dist-info/DESCRIPTION.rst
example2-0.1.dist-info/METADATA
example2-0.1.dist-info/RECORD
example2-0.1.dist-info/WHEEL
example2-0.1.dist-info/metadata.json
example2-0.1.dist-info/top_level.txt
example2_module/__init__.py
example2_module/example_aspp.py
