Metadata-Version: 2.0
Name: example2
Version: 0.1
Summary: The funniest joke in the world
Home-page: http://github.com/marineF/georgette
Author: Georgette
Author-email: flyingcircus@example.com
License: MIT
Platform: UNKNOWN
